{
    "version": "0.17.538",
    "description": "API Support for your favorite torrent trackers",
    "homepage": "https://github.com/Jackett/Jackett",
    "license": "GPL-2.0-or-later",
    "url": "https://github.com/Jackett/Jackett/releases/download/v0.17.538/Jackett.Binaries.Windows.zip",
    "hash": "bedcdbd722af72a89d89c5ebee68289df5fde92718b95829360a568ffd8384c2",
    "shortcuts": [
        [
            "Jackett\\JackettTray.exe",
            "Jackett"
        ]
    ],
    "checkver": "github",
    "autoupdate": {
        "url": "https://github.com/Jackett/Jackett/releases/download/v$version/Jackett.Binaries.Windows.zip"
    }
}
