{
    "version": "0.18.599",
    "description": "API Support for your favorite torrent trackers",
    "homepage": "https://github.com/Jackett/Jackett",
    "license": "GPL-2.0-or-later",
    "url": "https://github.com/Jackett/Jackett/releases/download/v0.18.599/Jackett.Binaries.Windows.zip",
    "hash": "92c08db1b299e50a2a794574cea4f12340aae6e1edde55e888237f5e4b6e6a83",
    "shortcuts": [
        [
            "Jackett\\JackettTray.exe",
            "Jackett"
        ]
    ],
    "checkver": "github",
    "autoupdate": {
        "url": "https://github.com/Jackett/Jackett/releases/download/v$version/Jackett.Binaries.Windows.zip"
    }
}
