{
    "version": "0.17.1027",
    "description": "API Support for your favorite torrent trackers",
    "homepage": "https://github.com/Jackett/Jackett",
    "license": "GPL-2.0-or-later",
    "url": "https://github.com/Jackett/Jackett/releases/download/v0.17.1027/Jackett.Binaries.Windows.zip",
    "hash": "e01cf1e95e9fe1c0578ebeeb32eaa95ea9b0f5f36913d1cbe10a98f741d38ae1",
    "shortcuts": [
        [
            "Jackett\\JackettTray.exe",
            "Jackett"
        ]
    ],
    "checkver": "github",
    "autoupdate": {
        "url": "https://github.com/Jackett/Jackett/releases/download/v$version/Jackett.Binaries.Windows.zip"
    }
}
