{
    "version": "0.17.668",
    "description": "API Support for your favorite torrent trackers",
    "homepage": "https://github.com/Jackett/Jackett",
    "license": "GPL-2.0-or-later",
    "url": "https://github.com/Jackett/Jackett/releases/download/v0.17.668/Jackett.Binaries.Windows.zip",
    "hash": "f14dc9e71e2490a3e5b247737810b9a3a90f7e807af212f935f9983cb47b4812",
    "shortcuts": [
        [
            "Jackett\\JackettTray.exe",
            "Jackett"
        ]
    ],
    "checkver": "github",
    "autoupdate": {
        "url": "https://github.com/Jackett/Jackett/releases/download/v$version/Jackett.Binaries.Windows.zip"
    }
}
